amsatop/__init__.py
amsatop/_htop/__init__.py
amsatop/_htop/htop.py
amsatop/_htop/htop_mock.py
amsatop/_htop/process.py
amsatop/_ui/__init__.py
amsatop/_ui/state.py
amsatop/_ui/tui.py
amsatop/utils/__init__.py
amsatop/utils/__stat_file.py
amsatop/utils/__status_file.py
amsatop-2.0.1.dist-info/WHEEL
amsatop-2.0.1.dist-info/METADATA
amsatop-2.0.1.dist-info/RECORD
