Metadata-Version: 2.3
Name: amsatop
Version: 2.0.1
Summary: Library for building your own htop from scratch, using python
Keywords: htop,process,tui,linux,terminal,monitor,amsatop
Author: Oriol Agost Batalla, Pablo Fraile Alonso, Ferran Aran Domingo
Author-email: Oriol Agost Batalla <oriol@agost.info>, Pablo Fraile Alonso <pablo@pablofraile.net>, Ferran Aran Domingo <ferran@aranferran.com>
License:                     GNU GENERAL PUBLIC LICENSE
Classifier: Development Status :: 3 - Alpha
Classifier: Intended Audience :: Developers
Classifier: Intended Audience :: Education
Classifier: License :: OSI Approved :: GNU General Public License v3 or later (GPLv3+)
Classifier: Operating System :: POSIX :: Linux
Classifier: Programming Language :: Python :: 3.13
Classifier: Programming Language :: Python :: 3 :: Only
Classifier: Topic :: System :: Monitoring
Classifier: Topic :: Utilities
Requires-Dist: pyfiglet>=1.0.4
Requires-Dist: textual>=5.3.0
Requires-Python: >=3.13
Project-URL: Documentation, https://el-despatx.github.io/amsatop/
Project-URL: Homepage, https://github.com/el-despatx/amsatop
Project-URL: Issues, https://github.com/el-despatx/amsatop/issues
Project-URL: Source, https://github.com/el-despatx/amsatop
